neuromeka_vfm/__init__.py
neuromeka_vfm/compression.py
neuromeka_vfm/grasp_gen.py
neuromeka_vfm/pickle_client.py
neuromeka_vfm/point_cloud_utils.py
neuromeka_vfm/pose_estimation.py
neuromeka_vfm/segmentation.py
neuromeka_vfm/upload_mesh.py
neuromeka_vfm/examples/__init__.py
neuromeka_vfm/examples/pose_demo.py
neuromeka_vfm-0.1.5.dist-info/licenses/LICENSE
neuromeka_vfm-0.1.5.dist-info/METADATA
neuromeka_vfm-0.1.5.dist-info/WHEEL
neuromeka_vfm-0.1.5.dist-info/entry_points.txt
neuromeka_vfm-0.1.5.dist-info/top_level.txt
neuromeka_vfm-0.1.5.dist-info/RECORD
