Metadata-Version: 2.4
Name: neuromeka_vfm
Version: 0.1.5
Summary: Client utilities for Neuromeka VFM FoundationPose RPC (upload meshes, call server)
Author: Neuromeka
License: MIT License
Classifier: Development Status :: 3 - Alpha
Classifier: Intended Audience :: Developers
Classifier: License :: OSI Approved :: MIT License
Classifier: Programming Language :: Python :: 3
Classifier: Programming Language :: Python :: 3.8
Classifier: Programming Language :: Python :: 3.9
Classifier: Programming Language :: Python :: 3.10
Classifier: Programming Language :: Python :: 3.11
Classifier: Programming Language :: Python :: 3.12
Requires-Python: >=3.8
License-File: LICENSE
Requires-Dist: numpy
Requires-Dist: pyzmq
Requires-Dist: paramiko
Requires-Dist: av
Requires-Dist: trimesh
Requires-Dist: tqdm
Dynamic: license-file
